vitamin_b/.version
vitamin_b/__init__.py
vitamin_b/gen_benchmark_pe.py
vitamin_b/plotting.py
vitamin_b/run_vitamin.py
vitamin_b/skyplotting.py
vitamin_b/models/CVAE_model.py
vitamin_b/models/__init__.py
vitamin_b/models/neural_networks/VI_decoder_r2.py
vitamin_b/models/neural_networks/VI_encoder_q.py
vitamin_b/models/neural_networks/VI_encoder_r1.py
vitamin_b/models/neural_networks/__init__.py
vitamin_b/models/neural_networks/batch_manager.py
vitamin_b/models/neural_networks/vae_utils.py
vitamin_b/params_files/__init__.py
vitamin_b/params_files/make_params_files.py
vitamin_b-0.2.2.dist-info/DESCRIPTION.rst
vitamin_b-0.2.2.dist-info/METADATA
vitamin_b-0.2.2.dist-info/RECORD
vitamin_b-0.2.2.dist-info/WHEEL
vitamin_b-0.2.2.dist-info/metadata.json
vitamin_b-0.2.2.dist-info/top_level.txt
